{
    "id": "el-125",
    "name": "Funglow",
    "class": "elestral",
    "render": "https://res.cloudinary.com/drmapg0vi/image/upload/f_auto/q_auto/v1731481808/Funglow_wpxgzx?_a=BATAXdXy0",
    "blurb": "Casters seeking Funglow often wait for thunderstorms, when these small Elestrals emerge from the forest into open meadows in hopes of attracting lightning strikes. Their tendency to illuminate hidden paths makes them beloved of travelers.",
    "updated_at": "2025-06-09T23:16:07.637Z",
    "elements": [
        "thunder"
    ]
}