{
    "id": "cd-1504",
    "base_name": "No Stone Unturned",
    "title": null,
    "set_number": "MR1-087",
    "sort_number": "MR1-087",
    "name": "No Stone Unturned",
    "alias": null,
    "card_type": "rune_invoke",
    "rarity": "common",
    "canvas": "regular_art",
    "frame_material": "stone",
    "artist": "Amalry",
    "set": "Moonrise",
    "set_id": "st-27",
    "subset": "main",
    "series": "First Edition",
    "series_id": "sr-5",
    "image": "https://res.cloudinary.com/drmapg0vi/image/upload/f_auto/q_auto/v1727924541/MR1-087NoStoneUnturned_hp8rg5?_a=BATAXdXy0",
    "render": "https://res.cloudinary.com/drmapg0vi/image/upload/f_auto/q_auto/v1734541492/NoStoneUnturned_borderized_pxfhcn?_a=BATAXdXy0",
    "creature_id": null,
    "total_cost": 2,
    "attack": null,
    "defense": null,
    "serialized_stellar": false,
    "serialized_population": null,
    "is_prize_card": false,
    "prize_rank": null,
    "printed_effect": "Search your deck for a {golem} Elestral\nand add it to your hand.",
    "effect": "Search your deck for a {golem} Elestral and add it to your hand.",
    "elements": [
        "earth"
    ],
    "cost": [
        "earth",
        "earth"
    ],
    "subclasses": [],
    "varaints": [
        "normal"
    ]
}