{
    "id": "cd-263",
    "base_name": "Lumaroo",
    "title": null,
    "set_number": "PR3-02",
    "sort_number": "PR3-02",
    "name": "Lumaroo",
    "alias": null,
    "card_type": "elestral",
    "rarity": "stellar_rare",
    "canvas": "regular_art",
    "frame_material": "stone",
    "artist": "Maumes",
    "set": "Daybreak Promos",
    "set_id": "st-40",
    "subset": "main",
    "series": "First Edition",
    "series_id": "sr-5",
    "image": "https://res.cloudinary.com/drmapg0vi/image/upload/f_auto/q_auto/v1723994612/PR3-02LumarooStellarNoWatermarkHolo_p2f3ub?_a=BATAXdXy0",
    "render": "https://res.cloudinary.com/drmapg0vi/image/upload/f_auto/q_auto/v1742156753/LumarooStellar_ffm2di?_a=BATAXdXy0",
    "creature_id": "el-195",
    "total_cost": 1,
    "attack": 5,
    "defense": 2,
    "serialized_stellar": false,
    "serialized_population": null,
    "is_prize_card": false,
    "prize_rank": null,
    "printed_effect": "When this Lumaroo destroys an opponent's\nElestral in battle that opponent must send the\ntop 3 cards from their deck to their Underworld.",
    "effect": "When this Lumaroo destroys an opponent's Elestral in battle that opponent must send the top 3 cards from their deck to the Underworld.",
    "elements": [
        "solar"
    ],
    "cost": [
        "solar"
    ],
    "subclasses": [
        "brute"
    ],
    "variants": [
        "holo"
    ]
}