{
    "id": "cd-2687",
    "base_name": "Hypnossum",
    "title": null,
    "set_number": "SS2-068",
    "sort_number": "SS2-068",
    "name": "Hypnossum",
    "alias": null,
    "card_type": "elestral",
    "rarity": "stellar_rare",
    "canvas": "regular_art",
    "frame_material": "stone",
    "artist": "Robb Hicks",
    "set": "Shattered Stars M14 - Pisces",
    "set_id": "st-87",
    "subset": "reverse_stellar",
    "series": "Shattered Stars",
    "series_id": "sr-9",
    "image": "https://res.cloudinary.com/drmapg0vi/image/upload/f_auto/q_auto/v1737776347/SS2-068RStellarHypnossum_gcf83l?_a=BATAXdXy0",
    "render": "https://res.cloudinary.com/drmapg0vi/image/upload/f_auto/q_auto/v1742154073/Hypnossum_mv4bqk?_a=BATAXdXy0",
    "creature_id": "el-248",
    "total_cost": 1,
    "attack": 1,
    "defense": 1,
    "serialized_stellar": false,
    "serialized_population": null,
    "is_prize_card": false,
    "prize_rank": null,
    "printed_effect": "When this Hypnossum is destroyed you\ncan Special Cast it from your Underworld in\nAttack Position Misenchanted.",
    "effect": "When this Hypnossum is destroyed you can Special Cast it from your Underworld in Attack Position Misenchanted.",
    "elements": [
        "lunar"
    ],
    "cost": [
        "lunar"
    ],
    "subclasses": [
        "brute",
        "ethereal"
    ],
    "variants": [
        "reverse_holo"
    ]
}