{
    "id": "cd-2685",
    "base_name": "Lunar Phase",
    "title": "New Moon",
    "set_number": "SS2-066",
    "sort_number": "SS2-066",
    "name": "Lunar Phase - New Moon",
    "alias": null,
    "card_type": "rune_invoke",
    "rarity": "rare",
    "canvas": "regular_art",
    "frame_material": "stone",
    "artist": "Simone Frigerio",
    "set": "Shattered Stars M14 - Pisces",
    "set_id": "st-87",
    "subset": "main",
    "series": "Shattered Stars",
    "series_id": "sr-9",
    "image": "https://res.cloudinary.com/drmapg0vi/image/upload/f_auto/q_auto/v1737776338/SS2-066LunarPhase-NewMoon_rtn77k?_a=BATAXdXy0",
    "render": "https://res.cloudinary.com/drmapg0vi/image/upload/f_auto/q_auto/v1734541451/Moon1_borderized_yxceqw?_a=BATAXdXy0",
    "creature_id": null,
    "total_cost": 1,
    "attack": null,
    "defense": null,
    "serialized_stellar": false,
    "serialized_population": null,
    "is_prize_card": false,
    "prize_rank": null,
    "printed_effect": "Target an Elestral on the field and\nSuppress it until the next turn.\nYou may Expend {lunar} equal to the targeted card’s\nEnchantment Cost and discard a Lunar Phase.\nIf you do, destroy it.",
    "effect": "Target an Elestral on the field and Suppress it until the next turn. You may Expend {lunar} equal to the targeted card's Enchantment Cost and discard a Lunar Phase. If you do, destroy it.",
    "elements": [
        "lunar"
    ],
    "cost": [
        "lunar"
    ],
    "subclasses": [],
    "varaints": [
        "holo"
    ]
}