{
    "id": "cd-650",
    "base_name": "Emphyrix",
    "title": null,
    "set_number": "BS1-034",
    "sort_number": "BS1-034",
    "name": "Emphyrix",
    "alias": null,
    "card_type": "elestral",
    "rarity": "rare",
    "canvas": "regular_art",
    "frame_material": "stone",
    "artist": "Élite4",
    "set": "Base",
    "set_id": "st-53",
    "subset": "main",
    "series": "First Edition",
    "series_id": "sr-5",
    "image": "https://res.cloudinary.com/drmapg0vi/image/upload/f_auto/q_auto/v1724088441/BS1-034EmphyrixNoWatermarkHolo_epszof?_a=BATAXdXy0",
    "render": "https://res.cloudinary.com/drmapg0vi/image/upload/f_auto/q_auto/v1731473646/Render_-_EmphyrixBS1-034_wkdgvv?_a=BATAXdXy0",
    "creature_id": "el-93",
    "total_cost": 1,
    "attack": 3,
    "defense": 3,
    "serialized_stellar": false,
    "serialized_population": null,
    "is_prize_card": false,
    "prize_rank": null,
    "printed_effect": "When this Emphyrix is destroyed in battle\nor by an opponent’s card effect you can\nExpend {fire}. If you do, during this turn’s\nEnd Phase you can Special Cast it\nfrom your Underworld.",
    "effect": "When this Emphyrix is destroyed in battle or by an opponent's card effect you can Expend {fire}. If you do, during this turn's End Phase you can Special Cast it from your Underworld.",
    "elements": [
        "fire"
    ],
    "cost": [
        "fire"
    ],
    "subclasses": [
        "avian",
        "ethereal"
    ],
    "variants": [
        "holo"
    ]
}